README.md
setup.py
snips_helper/__init__.py
snips_helper/bundle.py
snips_helper/console_helper.py
snips_helper/intent.py
snips_helper/intent_parser.py
snips_helper/slot_parser.py
snips_helper.egg-info/PKG-INFO
snips_helper.egg-info/SOURCES.txt
snips_helper.egg-info/dependency_links.txt
snips_helper.egg-info/not-zip-safe
snips_helper.egg-info/requires.txt
snips_helper.egg-info/top_level.txt