Metadata-Version: 1.0
Name: snips-helper
Version: 0.5
Summary: Snips.ai Helper
Home-page: http://github.com/uchagani/snips_helper
Author: Umair Chagani
Author-email: umair.chagani@gmail.com
License: MIT
Platform: UNKNOWN
